bp_percentile/__init__.py
bp_percentile/__main__.py
bp_percentile-0.6.0.dist-info/METADATA
bp_percentile-0.6.0.dist-info/WHEEL
bp_percentile-0.6.0.dist-info/entry_points.txt
bp_percentile-0.6.0.dist-info/top_level.txt
bp_percentile-0.6.0.dist-info/RECORD
